briscola_gym/__init__.py
briscola_gym/card.py
briscola_gym/game.py
briscola_gym/game_rules.py
briscola_gym/player/__init__.py
briscola_gym/player/base_player.py
briscola_gym/player/epsgreedy_player.py
briscola_gym/player/human_player.py
briscola_gym/player/random_player.py
briscola_gym/seed.py
briscola_gym/state.py
briscola_gym-0.1.0.dist-info/WHEEL
briscola_gym-0.1.0.dist-info/METADATA
briscola_gym-0.1.0.dist-info/RECORD
